metaindex/__init__.py
metaindex/cache.py
metaindex/cacheentry.py
metaindex/cli.py
metaindex/client.py
metaindex/configuration.py
metaindex/find.py
metaindex/fuse.py
metaindex/humanizer.py
metaindex/indexer.py
metaindex/indexers.py
metaindex/json.py
metaindex/logger.py
metaindex/main.py
metaindex/ocr.py
metaindex/opf.py
metaindex/proto.py
metaindex/query.py
metaindex/ruleindexer.py
metaindex/server.py
metaindex/shared.py
metaindex/sql.py
metaindex/stores.py
metaindex/version.py
metaindex/xmlproxy.py
metaindex/yaml.py
metaindex/docs/cmdoptions.html
metaindex/docs/metaindex.html
metaindex/indexers/__init__.py
metaindex/indexers/abc.py
metaindex/indexers/audio.py
metaindex/indexers/collections.py
metaindex/indexers/comicbook.py
metaindex/indexers/epub.py
metaindex/indexers/filetags.py
metaindex/indexers/gpx.py
metaindex/indexers/html.py
metaindex/indexers/images.py
metaindex/indexers/ooxml.py
metaindex/indexers/opendocument.py
metaindex/indexers/pdf.py
metaindex/indexers/ruleindexer.py
metaindex-2.3.0.data/data/share/doc/metaindex/metaindex.conf
metaindex-2.3.0.data/data/share/doc/metaindex/examples/indexing.py
metaindex-2.3.0.data/data/share/man/man1/metaindex.1
metaindex-2.3.0.dist-info/METADATA
metaindex-2.3.0.dist-info/WHEEL
metaindex-2.3.0.dist-info/entry_points.txt
metaindex-2.3.0.dist-info/top_level.txt
metaindex-2.3.0.dist-info/RECORD
