Metadata-Version: 2.1
Name: metaindex
Version: 2.3.0
Summary: Utilities to tag files
Home-page: https://vonshednob.cc/metaindex
Author: R
Author-email: devel+metaindex@kakaomilchkuh.de
Classifier: Development Status :: 3 - Alpha
Classifier: Environment :: Console
Classifier: Intended Audience :: End Users/Desktop
Classifier: Intended Audience :: Developers
Classifier: License :: OSI Approved :: MIT License
Classifier: Natural Language :: English
Classifier: Programming Language :: Python :: 3.6
Classifier: Topic :: Text Processing :: Indexing
Requires-Python: >=3.6
Provides-Extra: all
Requires-Dist: mutagen ; extra == 'all'
Requires-Dist: pillow ; extra == 'all'
Requires-Dist: pillow (>=6.2.0) ; extra == 'all'
Requires-Dist: pyxdg ; extra == 'all'
Requires-Dist: defusedxml ; extra == 'all'
Requires-Dist: pyyaml ; extra == 'all'
Requires-Dist: pyexiv2 ; extra == 'all'
Requires-Dist: pypdf ; extra == 'all'
Provides-Extra: audio
Requires-Dist: mutagen ; extra == 'audio'
Provides-Extra: ebook
Requires-Dist: defusedxml ; extra == 'ebook'
Provides-Extra: fuse
Requires-Dist: trio ; extra == 'fuse'
Requires-Dist: pyfuse3 ; extra == 'fuse'
Provides-Extra: image
Requires-Dist: pyexiv2 ; extra == 'image'
Requires-Dist: pillow ; extra == 'image'
Provides-Extra: ocr
Requires-Dist: pillow (>=6.2.0) ; extra == 'ocr'
Provides-Extra: pdf
Requires-Dist: pypdf ; extra == 'pdf'
Provides-Extra: video
Requires-Dist: mutagen ; extra == 'video'
Provides-Extra: xdg
Requires-Dist: pyxdg ; extra == 'xdg'
Provides-Extra: yaml
Requires-Dist: pyyaml ; extra == 'yaml'
